{"id":130426,"parent_id":1304,"code":"130426000000","name":"\u6d89\u53bf","level":2,"children":[{"id":130426001,"parent_id":130426,"code":"130426001000","name":"\u5e73\u5b89\u8857\u9053","level":3,"children":[]},{"id":130426101,"parent_id":130426,"code":"130426101000","name":"\u6cb3\u5357\u5e97\u9547","level":3,"children":[]},{"id":130426102,"parent_id":130426,"code":"130426102000","name":"\u7d22\u5821\u9547","level":3,"children":[]},{"id":130426103,"parent_id":130426,"code":"130426103000","name":"\u897f\u620c\u9547","level":3,"children":[]},{"id":130426104,"parent_id":130426,"code":"130426104000","name":"\u4e95\u5e97\u9547","level":3,"children":[]},{"id":130426105,"parent_id":130426,"code":"130426105000","name":"\u66f4\u4e50\u9547","level":3,"children":[]},{"id":130426106,"parent_id":130426,"code":"130426106000","name":"\u56fa\u65b0\u9547","level":3,"children":[]},{"id":130426107,"parent_id":130426,"code":"130426107000","name":"\u897f\u8fbe\u9547","level":3,"children":[]},{"id":130426108,"parent_id":130426,"code":"130426108000","name":"\u504f\u57ce\u9547","level":3,"children":[]},{"id":1304262,"parent_id":130426,"code":"130426200000","name":"\u795e\u5934\u4e61","level":3,"children":[]},{"id":130426201,"parent_id":130426,"code":"130426201000","name":"\u8fbd\u57ce\u4e61","level":3,"children":[]},{"id":130426202,"parent_id":130426,"code":"130426202000","name":"\u504f\u5e97\u4e61","level":3,"children":[]},{"id":130426203,"parent_id":130426,"code":"130426203000","name":"\u9f99\u864e\u4e61","level":3,"children":[]},{"id":130426204,"parent_id":130426,"code":"130426204000","name":"\u6728\u4e95\u4e61","level":3,"children":[]},{"id":130426205,"parent_id":130426,"code":"130426205000","name":"\u5173\u9632\u4e61","level":3,"children":[]},{"id":130426206,"parent_id":130426,"code":"130426206000","name":"\u5408\u6f33\u4e61","level":3,"children":[]},{"id":130426207,"parent_id":130426,"code":"130426207000","name":"\u9e7f\u5934\u4e61","level":3,"children":[]},{"id":1304264,"parent_id":130426,"code":"130426400000","name":"\u6d89\u57ce\u9547","level":3,"children":[]}]}