{"id":430722,"parent_id":4307,"code":"430722000000","name":"\u6c49\u5bff\u53bf","level":2,"children":[{"id":430722001,"parent_id":430722,"code":"430722001000","name":"\u9f99\u9633\u8857\u9053","level":3,"children":[]},{"id":430722002,"parent_id":430722,"code":"430722002000","name":"\u8fb0\u9633\u8857\u9053","level":3,"children":[]},{"id":430722003,"parent_id":430722,"code":"430722003000","name":"\u6ca7\u6d6a\u8857\u9053","level":3,"children":[]},{"id":430722004,"parent_id":430722,"code":"430722004000","name":"\u682a\u6728\u5c71\u8857\u9053","level":3,"children":[]},{"id":430722101,"parent_id":430722,"code":"430722101000","name":"\u848b\u5bb6\u5634\u9547","level":3,"children":[]},{"id":430722102,"parent_id":430722,"code":"430722102000","name":"\u5ca9\u6c6a\u6e56\u9547","level":3,"children":[]},{"id":430722103,"parent_id":430722,"code":"430722103000","name":"\u5761\u5934\u9547","level":3,"children":[]},{"id":430722104,"parent_id":430722,"code":"430722104000","name":"\u9149\u6e2f\u9547","level":3,"children":[]},{"id":430722105,"parent_id":430722,"code":"430722105000","name":"\u6d32\u53e3\u9547","level":3,"children":[]},{"id":430722106,"parent_id":430722,"code":"430722106000","name":"\u7f50\u5934\u5634\u9547","level":3,"children":[]},{"id":430722107,"parent_id":430722,"code":"430722107000","name":"\u6ca7\u6e2f\u9547","level":3,"children":[]},{"id":430722108,"parent_id":430722,"code":"430722108000","name":"\u6731\u5bb6\u94fa\u9547","level":3,"children":[]},{"id":430722109,"parent_id":430722,"code":"430722109000","name":"\u592a\u5b50\u5e99\u9547","level":3,"children":[]},{"id":430722111,"parent_id":430722,"code":"430722111000","name":"\u5d14\u5bb6\u6865\u9547","level":3,"children":[]},{"id":430722112,"parent_id":430722,"code":"430722112000","name":"\u519b\u5c71\u94fa\u9547","level":3,"children":[]},{"id":430722113,"parent_id":430722,"code":"430722113000","name":"\u767e\u7984\u6865\u9547","level":3,"children":[]},{"id":430722114,"parent_id":430722,"code":"430722114000","name":"\u897f\u6e56\u9547","level":3,"children":[]},{"id":430722115,"parent_id":430722,"code":"430722115000","name":"\u6d0b\u6dd8\u6e56\u9547","level":3,"children":[]},{"id":430722117,"parent_id":430722,"code":"430722117000","name":"\u4e30\u5bb6\u94fa\u9547","level":3,"children":[]},{"id":430722118,"parent_id":430722,"code":"430722118000","name":"\u9f99\u6f6d\u6865\u9547","level":3,"children":[]},{"id":430722205,"parent_id":430722,"code":"430722205000","name":"\u8042\u5bb6\u6865\u4e61","level":3,"children":[]},{"id":430722206,"parent_id":430722,"code":"430722206000","name":"\u6bdb\u5bb6\u6ee9\u56de\u65cf\u7ef4\u543e\u5c14\u65cf\u4e61","level":3,"children":[]},{"id":430722501,"parent_id":430722,"code":"430722501000","name":"\u897f\u6e56\u7ba1\u7406\u533a","level":3,"children":[]}]}