{"id":500241,"parent_id":5002,"code":"500241000000","name":"\u79c0\u5c71\u571f\u5bb6\u65cf\u82d7\u65cf\u81ea\u6cbb\u53bf","level":2,"children":[{"id":500241001,"parent_id":500241,"code":"500241001000","name":"\u4e2d\u548c\u8857\u9053","level":3,"children":[]},{"id":500241002,"parent_id":500241,"code":"500241002000","name":"\u4e4c\u6768\u8857\u9053","level":3,"children":[]},{"id":500241003,"parent_id":500241,"code":"500241003000","name":"\u5e73\u51ef\u8857\u9053","level":3,"children":[]},{"id":500241004,"parent_id":500241,"code":"500241004000","name":"\u5b98\u5e84\u8857\u9053","level":3,"children":[]},{"id":500241005,"parent_id":500241,"code":"500241005000","name":"\u6e05\u6eaa\u573a\u8857\u9053","level":3,"children":[]},{"id":500241103,"parent_id":500241,"code":"500241103000","name":"\u9698\u53e3\u9547","level":3,"children":[]},{"id":500241104,"parent_id":500241,"code":"500241104000","name":"\u6eb6\u6eaa\u9547","level":3,"children":[]},{"id":500241106,"parent_id":500241,"code":"500241106000","name":"\u9f99\u6c60\u9547","level":3,"children":[]},{"id":500241107,"parent_id":500241,"code":"500241107000","name":"\u77f3\u5824\u9547","level":3,"children":[]},{"id":500241108,"parent_id":500241,"code":"500241108000","name":"\u5ce8\u6eb6\u9547","level":3,"children":[]},{"id":500241109,"parent_id":500241,"code":"500241109000","name":"\u6d2a\u5b89\u9547","level":3,"children":[]},{"id":50024111,"parent_id":500241,"code":"500241110000","name":"\u96c5\u6c5f\u9547","level":3,"children":[]},{"id":500241111,"parent_id":500241,"code":"500241111000","name":"\u77f3\u8036\u9547","level":3,"children":[]},{"id":500241112,"parent_id":500241,"code":"500241112000","name":"\u6885\u6c5f\u9547","level":3,"children":[]},{"id":500241113,"parent_id":500241,"code":"500241113000","name":"\u5170\u6865\u9547","level":3,"children":[]},{"id":500241114,"parent_id":500241,"code":"500241114000","name":"\u818f\u7530\u9547","level":3,"children":[]},{"id":500241115,"parent_id":500241,"code":"500241115000","name":"\u6eaa\u53e3\u9547","level":3,"children":[]},{"id":500241116,"parent_id":500241,"code":"500241116000","name":"\u5999\u6cc9\u9547","level":3,"children":[]},{"id":500241117,"parent_id":500241,"code":"500241117000","name":"\u5b8b\u519c\u9547","level":3,"children":[]},{"id":500241118,"parent_id":500241,"code":"500241118000","name":"\u91cc\u4ec1\u9547","level":3,"children":[]},{"id":500241119,"parent_id":500241,"code":"500241119000","name":"\u949f\u7075\u9547","level":3,"children":[]},{"id":50024112,"parent_id":500241,"code":"500241120000","name":"\u9f99\u51e4\u575d\u9547","level":3,"children":[]},{"id":500241121,"parent_id":500241,"code":"500241121000","name":"\u6d8c\u6d1e\u9547","level":3,"children":[]},{"id":500241207,"parent_id":500241,"code":"500241207000","name":"\u6d77\u6d0b\u4e61","level":3,"children":[]},{"id":500241208,"parent_id":500241,"code":"500241208000","name":"\u5927\u6eaa\u4e61","level":3,"children":[]},{"id":500241214,"parent_id":500241,"code":"500241214000","name":"\u4e2d\u5e73\u4e61","level":3,"children":[]},{"id":500241215,"parent_id":500241,"code":"500241215000","name":"\u5c91\u6eaa\u4e61","level":3,"children":[]}]}