{"id":510802,"parent_id":5108,"code":"510802000000","name":"\u5229\u5dde\u533a","level":2,"children":[{"id":510802001,"parent_id":510802,"code":"510802001000","name":"\u4e1c\u575d\u8857\u9053","level":3,"children":[]},{"id":510802002,"parent_id":510802,"code":"510802002000","name":"\u5609\u9675\u8857\u9053","level":3,"children":[]},{"id":510802003,"parent_id":510802,"code":"510802003000","name":"\u6cb3\u897f\u8857\u9053","level":3,"children":[]},{"id":510802004,"parent_id":510802,"code":"510802004000","name":"\u96ea\u5cf0\u8857\u9053","level":3,"children":[]},{"id":510802005,"parent_id":510802,"code":"510802005000","name":"\u5357\u6cb3\u8857\u9053","level":3,"children":[]},{"id":510802006,"parent_id":510802,"code":"510802006000","name":"\u4e0a\u897f\u8857\u9053","level":3,"children":[]},{"id":510802011,"parent_id":510802,"code":"510802011000","name":"\u4e07\u7f18\u8857\u9053","level":3,"children":[]},{"id":5108021,"parent_id":510802,"code":"510802100000","name":"\u8363\u5c71\u9547","level":3,"children":[]},{"id":510802101,"parent_id":510802,"code":"510802101000","name":"\u5927\u77f3\u9547","level":3,"children":[]},{"id":510802102,"parent_id":510802,"code":"510802102000","name":"\u76d8\u9f99\u9547","level":3,"children":[]},{"id":510802103,"parent_id":510802,"code":"510802103000","name":"\u5b9d\u8f6e\u9547","level":3,"children":[]},{"id":510802105,"parent_id":510802,"code":"510802105000","name":"\u4e09\u5806\u9547","level":3,"children":[]},{"id":5108022,"parent_id":510802,"code":"510802200000","name":"\u767d\u671d\u4e61","level":3,"children":[]},{"id":510802201,"parent_id":510802,"code":"510802201000","name":"\u91d1\u6d1e\u4e61","level":3,"children":[]},{"id":510802202,"parent_id":510802,"code":"510802202000","name":"\u9f99\u6f6d\u4e61","level":3,"children":[]}]}