{"id":511381,"parent_id":5113,"code":"511381000000","name":"\u9606\u4e2d\u5e02","level":2,"children":[{"id":511381001,"parent_id":511381,"code":"511381001000","name":"\u4fdd\u5b81\u8857\u9053","level":3,"children":[]},{"id":511381003,"parent_id":511381,"code":"511381003000","name":"\u6c99\u6eaa\u8857\u9053","level":3,"children":[]},{"id":511381004,"parent_id":511381,"code":"511381004000","name":"\u4e03\u91cc\u8857\u9053","level":3,"children":[]},{"id":511381005,"parent_id":511381,"code":"511381005000","name":"\u6c5f\u5357\u8857\u9053","level":3,"children":[]},{"id":511381006,"parent_id":511381,"code":"511381006000","name":"\u6cb3\u6eaa\u8857\u9053","level":3,"children":[]},{"id":511381103,"parent_id":511381,"code":"511381103000","name":"\u5f6d\u57ce\u9547","level":3,"children":[]},{"id":511381105,"parent_id":511381,"code":"511381105000","name":"\u67cf\u57ad\u9547","level":3,"children":[]},{"id":511381106,"parent_id":511381,"code":"511381106000","name":"\u98de\u51e4\u9547","level":3,"children":[]},{"id":511381107,"parent_id":511381,"code":"511381107000","name":"\u601d\u4f9d\u9547","level":3,"children":[]},{"id":511381108,"parent_id":511381,"code":"511381108000","name":"\u6587\u6210\u9547","level":3,"children":[]},{"id":511381109,"parent_id":511381,"code":"511381109000","name":"\u4e8c\u9f99\u9547","level":3,"children":[]},{"id":51138111,"parent_id":511381,"code":"511381110000","name":"\u77f3\u6ee9\u9547","level":3,"children":[]},{"id":511381111,"parent_id":511381,"code":"511381111000","name":"\u8001\u89c2\u9547","level":3,"children":[]},{"id":511381112,"parent_id":511381,"code":"511381112000","name":"\u9f99\u6cc9\u9547","level":3,"children":[]},{"id":511381113,"parent_id":511381,"code":"511381113000","name":"\u5343\u4f5b\u9547","level":3,"children":[]},{"id":511381114,"parent_id":511381,"code":"511381114000","name":"\u671b\u57ad\u9547","level":3,"children":[]},{"id":511381116,"parent_id":511381,"code":"511381116000","name":"\u5999\u9ad8\u9547","level":3,"children":[]},{"id":511381117,"parent_id":511381,"code":"511381117000","name":"\u6d2a\u5c71\u9547","level":3,"children":[]},{"id":51138112,"parent_id":511381,"code":"511381120000","name":"\u6c34\u89c2\u9547","level":3,"children":[]},{"id":511381121,"parent_id":511381,"code":"511381121000","name":"\u91d1\u57ad\u9547","level":3,"children":[]},{"id":511381122,"parent_id":511381,"code":"511381122000","name":"\u7389\u53f0\u9547","level":3,"children":[]},{"id":511381124,"parent_id":511381,"code":"511381124000","name":"\u6728\u5170\u9547","level":3,"children":[]},{"id":511381127,"parent_id":511381,"code":"511381127000","name":"\u4e94\u9a6c\u9547","level":3,"children":[]},{"id":511381128,"parent_id":511381,"code":"511381128000","name":"\u5929\u5bab\u9547","level":3,"children":[]},{"id":511381212,"parent_id":511381,"code":"511381212000","name":"\u6865\u697c\u4e61","level":3,"children":[]},{"id":511381219,"parent_id":511381,"code":"511381219000","name":"\u535a\u6811\u56de\u65cf\u4e61","level":3,"children":[]},{"id":511381234,"parent_id":511381,"code":"511381234000","name":"\u5cf0\u5360\u4e61","level":3,"children":[]},{"id":511381235,"parent_id":511381,"code":"511381235000","name":"\u9e64\u5cf0\u4e61","level":3,"children":[]}]}