{"id":530921,"parent_id":5309,"code":"530921000000","name":"\u51e4\u5e86\u53bf","level":2,"children":[{"id":530921101,"parent_id":530921,"code":"530921101000","name":"\u51e4\u5c71\u9547","level":3,"children":[]},{"id":530921102,"parent_id":530921,"code":"530921102000","name":"\u9c81\u53f2\u9547","level":3,"children":[]},{"id":530921103,"parent_id":530921,"code":"530921103000","name":"\u5c0f\u6e7e\u9547","level":3,"children":[]},{"id":530921104,"parent_id":530921,"code":"530921104000","name":"\u8425\u76d8\u9547","level":3,"children":[]},{"id":530921105,"parent_id":530921,"code":"530921105000","name":"\u4e09\u5c94\u6cb3\u9547","level":3,"children":[]},{"id":530921106,"parent_id":530921,"code":"530921106000","name":"\u52d0\u4f51\u9547","level":3,"children":[]},{"id":530921107,"parent_id":530921,"code":"530921107000","name":"\u96ea\u5c71\u9547","level":3,"children":[]},{"id":530921108,"parent_id":530921,"code":"530921108000","name":"\u6d1b\u515a\u9547","level":3,"children":[]},{"id":530921201,"parent_id":530921,"code":"530921201000","name":"\u8bd7\u793c\u4e61","level":3,"children":[]},{"id":530921202,"parent_id":530921,"code":"530921202000","name":"\u65b0\u534e\u5f5d\u65cf\u82d7\u65cf\u4e61","level":3,"children":[]},{"id":530921204,"parent_id":530921,"code":"530921204000","name":"\u5927\u5bfa\u4e61","level":3,"children":[]},{"id":530921206,"parent_id":530921,"code":"530921206000","name":"\u8170\u8857\u5f5d\u65cf\u4e61","level":3,"children":[]},{"id":530921207,"parent_id":530921,"code":"530921207000","name":"\u90ed\u5927\u5be8\u5f5d\u65cf\u767d\u65cf\u4e61","level":3,"children":[]}]}