{"id":540525,"parent_id":5405,"code":"540525000000","name":"\u66f2\u677e\u53bf","level":2,"children":[{"id":5405251,"parent_id":540525,"code":"540525100000","name":"\u66f2\u677e\u9547","level":3,"children":[]},{"id":540525101,"parent_id":540525,"code":"540525101000","name":"\u7f57\u5e03\u6c99\u9547","level":3,"children":[]},{"id":5405252,"parent_id":540525,"code":"540525200000","name":"\u4e0b\u6c5f\u4e61","level":3,"children":[]},{"id":540525201,"parent_id":540525,"code":"540525201000","name":"\u90b1\u591a\u6c5f\u4e61","level":3,"children":[]},{"id":540525202,"parent_id":540525,"code":"540525202000","name":"\u5806\u968f\u4e61","level":3,"children":[]}]}