{"id":632801,"parent_id":6328,"code":"632801000000","name":"\u683c\u5c14\u6728\u5e02","level":2,"children":[{"id":632801001,"parent_id":632801,"code":"632801001000","name":"\u6606\u4ed1\u8def\u8857\u9053","level":3,"children":[]},{"id":632801002,"parent_id":632801,"code":"632801002000","name":"\u9ec4\u6cb3\u8def\u8857\u9053","level":3,"children":[]},{"id":632801003,"parent_id":632801,"code":"632801003000","name":"\u91d1\u5cf0\u8def\u8857\u9053","level":3,"children":[]},{"id":632801004,"parent_id":632801,"code":"632801004000","name":"\u6cb3\u897f\u8857\u9053","level":3,"children":[]},{"id":632801005,"parent_id":632801,"code":"632801005000","name":"\u897f\u85cf\u8def\u8857\u9053","level":3,"children":[]},{"id":6328011,"parent_id":632801,"code":"632801100000","name":"\u90ed\u52d2\u6728\u5fb7\u9547","level":3,"children":[]},{"id":632801101,"parent_id":632801,"code":"632801101000","name":"\u5510\u53e4\u62c9\u9547","level":3,"children":[]},{"id":6328012,"parent_id":632801,"code":"632801200000","name":"\u5927\u683c\u52d2\u4e61","level":3,"children":[]},{"id":632801201,"parent_id":632801,"code":"632801201000","name":"\u4e4c\u56fe\u7f8e\u4ec1\u4e61","level":3,"children":[]},{"id":6328014,"parent_id":632801,"code":"632801400000","name":"\u5bdf\u5c14\u6c57\u5de5\u884c\u59d4","level":3,"children":[]},{"id":632801401,"parent_id":632801,"code":"632801401000","name":"\u683c\u5c14\u6728\u519c\u57a6\u6709\u9650\u516c\u53f8","level":3,"children":[]}]}